.gitignore
.travis.yml
LICENSE
MANIFEST.in
README.md
requirements-dev.txt
requirements-doc.txt
requirements.txt
setup.py
brainpy/__init__.py
brainpy/errors.py
brainpy/inputs.py
brainpy/measure.py
brainpy/profile.py
brainpy/running.py
brainpy/backend/__init__.py
brainpy/connectivity/__init__.py
brainpy/connectivity/base.py
brainpy/connectivity/methods.py
brainpy/core/__init__.py
brainpy/core/base.py
brainpy/core/constants.py
brainpy/core/ion_channels.py
brainpy/core/network.py
brainpy/core/neurons.py
brainpy/core/runner.py
brainpy/core/synapses.py
brainpy/core/types.py
brainpy/dynamics/__init__.py
brainpy/dynamics/bifurcation_analyzer.py
brainpy/dynamics/phase_portrait_analyzer.py
brainpy/dynamics/solver.py
brainpy/dynamics/utils.py
brainpy/integration/__init__.py
brainpy/integration/constants.py
brainpy/integration/diff_equation.py
brainpy/integration/integrator.py
brainpy/integration/methods.py
brainpy/integration/sympy_tools.py
brainpy/tools/__init__.py
brainpy/tools/ast2code.py
brainpy/tools/codes.py
brainpy/tools/dicts.py
brainpy/tools/functions.py
brainpy/tools/logger.py
brainpy/visualization/__init__.py
brainpy/visualization/figures.py
brainpy/visualization/plots.py
brainpy/visualization/styles.py
scikit_brain.egg-info/PKG-INFO
scikit_brain.egg-info/SOURCES.txt
scikit_brain.egg-info/dependency_links.txt
scikit_brain.egg-info/requires.txt
scikit_brain.egg-info/top_level.txt